README.md
setup.py
keysafe/__init__.py
keysafe.egg-info/PKG-INFO
keysafe.egg-info/SOURCES.txt
keysafe.egg-info/dependency_links.txt
keysafe.egg-info/top_level.txt
keysafe/src/__init__.py
keysafe/src/safe.py