Metadata-Version: 2.1
Name: keysafe
Version: 1.1
Summary: Keyring-based utilitiy for enchanced safekeeping of login informaiton.
Home-page: UNKNOWN
Author: ViperVit (V.Vigasin)
Author-email: vitolg1@gmail.com
License: Apache
Platform: UNKNOWN
Classifier: Programming Language :: Python :: 3
Classifier: Intended Audience :: Developers
Classifier: Topic :: Utilities
Classifier: Topic :: Security
